LICENSE.txt
README.md
pyproject.toml
setup.cfg
setup.py
fastapi_camelcase/__init__.py
fastapi_camelcase/py.typed
fastapi_camelcase.egg-info/PKG-INFO
fastapi_camelcase.egg-info/SOURCES.txt
fastapi_camelcase.egg-info/dependency_links.txt
fastapi_camelcase.egg-info/not-zip-safe
fastapi_camelcase.egg-info/requires.txt
fastapi_camelcase.egg-info/top_level.txt