Metadata-Version: 2.1
Name: fastapi-camelcase
Version: 2.0.0
Summary: Package provides an easy way to have camelcase request/response bodies for Pydantic
Home-page: https://nf1s.github.io/fastapi-camelcase/
Author: Ahmed Nafies
Author-email: ahmed.nafies@gmail.com
License: MIT
Project-URL: Documentation, https://nf1s.github.io/fastapi-camelcase/
Project-URL: Source, https://github.com/nf1s/fastapi-camelcase
Platform: UNKNOWN
Classifier: Intended Audience :: Developers
Classifier: Topic :: Utilities
Classifier: License :: OSI Approved :: MIT License
Classifier: Programming Language :: Python :: 3
Classifier: Programming Language :: Python :: 3.9
Classifier: Programming Language :: Python :: 3.10
Requires-Python: >=3.9
License-File: LICENSE.txt
